ipyvizzu_story-0.12.0.dist-info/METADATA
ipyvizzu_story-0.12.0.dist-info/WHEEL
ipyvizzu_story-0.12.0.dist-info/entry_points.txt
ipyvizzu_story-0.12.0.dist-info/licenses/LICENSE
ipyvizzustory/__init__.py
ipyvizzustory/__version__.py
ipyvizzustory/env/__init__.py
ipyvizzustory/env/ipy/__init__.py
ipyvizzustory/env/ipy/story.py
ipyvizzustory/env/pn/__init__.py
ipyvizzustory/env/pn/story.py
ipyvizzustory/env/py/__init__.py
ipyvizzustory/env/py/story.py
ipyvizzustory/env/st/__init__.py
ipyvizzustory/env/st/story.py
ipyvizzustory/py.typed
ipyvizzustory/storylib/__init__.py
ipyvizzustory/storylib/animation.py
ipyvizzustory/storylib/story.py
ipyvizzustory/storylib/template.py
ipyvizzu_story-0.12.0.dist-info/RECORD
