Metadata-Version: 2.1
Name: ipyvizzu-story
Version: 0.12.0
Summary: Build, present and share animated data stories in Jupyter Notebook and similar environments.
Keywords: python,template,notebook,interactive,presentation,data-visualization,charting,datastory,datastorytelling
Author-Email: "Vizzu Inc." <hello@vizzu.io>
License: Apache-2.0
Classifier: Environment :: Console
Classifier: License :: OSI Approved :: Apache Software License
Classifier: Operating System :: OS Independent
Classifier: Programming Language :: Python :: 3
Project-URL: Homepage, https://ipyvizzu-story.vizzuhq.com
Project-URL: Documentation, https://ipyvizzu-story.vizzuhq.com
Project-URL: Source, https://github.com/vizzuhq/ipyvizzu-story
Project-URL: Tracker, https://github.com/vizzuhq/ipyvizzu-story/issues
Requires-Python: >=3.9
Requires-Dist: ipyvizzu<1.0.0
Provides-Extra: jupyter
Requires-Dist: IPython; extra == "jupyter"
Provides-Extra: streamlit
Requires-Dist: streamlit; extra == "streamlit"
Provides-Extra: panel
Requires-Dist: panel; extra == "panel"
